examine/__init__.py
examine/examine.py
examine-1.0.1.dist-info/DESCRIPTION.rst
examine-1.0.1.dist-info/METADATA
examine-1.0.1.dist-info/RECORD
examine-1.0.1.dist-info/WHEEL
examine-1.0.1.dist-info/metadata.json
examine-1.0.1.dist-info/top_level.txt
