Metadata-Version: 2.0
Name: examine
Version: 1.0.1
Summary: A simple library for examining complex data structures.
Home-page: https://github.com/Jazzer360/python-examine
Author: Derek Jass
Author-email: jazzer36@gmail.com
License: MIT
Keywords: examine data structures dict parsing
Platform: UNKNOWN
Classifier: Development Status :: 4 - Beta
Classifier: Intended Audience :: Developers
Classifier: License :: OSI Approved :: MIT License
Classifier: Programming Language :: Python :: 2.7
Classifier: Programming Language :: Python :: 3.4
